chonkie_chunk_utils/__init__.py
chonkie_chunk_utils/merge_adjacent_chunks.py
chonkie_chunk_utils/render_chunks.py
chonkie_chunk_utils/sort_chunks.py
chonkie_chunk_utils/formatters/__init__.py
chonkie_chunk_utils/formatters/format_fn.py
chonkie_chunk_utils/formatters/jsonify.py
chonkie_chunk_utils/formatters/toonify.py
chonkie_chunk_utils/formatters/xmlify.py
chonkie_chunk_utils/utils/__init__.py
chonkie_chunk_utils/utils/is_adjacent_chunks.py
chonkie_chunk_utils/utils/is_sorted_chunks.py
chonkie_chunk_utils/utils/merge_chunks.py
chonkie_chunk_utils-0.2.0.dist-info/METADATA
chonkie_chunk_utils-0.2.0.dist-info/WHEEL
chonkie_chunk_utils-0.2.0.dist-info/licenses/LICENSE
chonkie_chunk_utils-0.2.0.dist-info/RECORD
