Metadata-Version: 2.4
Name: chonkie-chunk-utils
Version: 0.2.0
Summary: Utility functions for managing and processing chonkie Chunk objects
Author-email: devcomfort <im@devcomfort.me>
License-File: LICENSE
Requires-Python: >=3.8
Requires-Dist: chonkie[all]>=1.4.1
Requires-Dist: loguru>=0.7.3
Requires-Dist: toolz>=1.1.0
Requires-Dist: toon-python>=0.1.2
Requires-Dist: typing-extensions>=4.15.0
